{"type": "FeatureCollection", "features": [{"type": "Feature", "properties": {"station_name": "station1", "depth_from": "[0.1 0.1]", "depth_to": "[0.1 0.1]", "network": "IMA-CAN1"}, "geometry": {"type": "Point", "coordinates": [8.62621, 44.68263]}}, {"type": "Feature", "properties": {"station_name": "station10", "depth_from": "[0.1 0.1]", "depth_to": "[0.1 0.1]", "network": "IMA-CAN1"}, "geometry": {"type": "Point", "coordinates": [8.62636, 44.68275]}}, {"type": "Feature", "properties": {"station_name": "station11", "depth_from": "[0.1 0.1]", "depth_to": "[0.1 0.1]", "network": "IMA-CAN1"}, "geometry": {"type": "Point", "coordinates": [8.6267, 44.68253]}}, {"type": "Feature", "properties": {"station_name": "station12", "depth_from": "[0.1 0.1]", "depth_to": "[0.1 0.1]", "network": "IMA-CAN1"}, "geometry": {"type": "Point", "coordinates": [8.62671, 44.68254]}}, {"type": "Feature", "properties": {"station_name": "station2", "depth_from": "[0.1 0.1]", "depth_to": "[0.1 0.1]", "network": "IMA-CAN1"}, "geometry": {"type": "Point", "coordinates": [8.62622, 44.68264]}}, {"type": "Feature", "properties": {"station_name": "station3", "depth_from": "[0.1 0.1]", "depth_to": "[0.1 0.1]", "network": "IMA-CAN1"}, "geometry": {"type": "Point", "coordinates": [8.62657, 44.68241]}}, {"type": "Feature", "properties": {"station_name": "station4", "depth_from": "[0.1 0.1]", "depth_to": "[0.1 0.1]", "network": "IMA-CAN1"}, "geometry": {"type": "Point", "coordinates": [8.62658, 44.68242]}}, {"type": "Feature", "properties": {"station_name": "station5", "depth_from": "[0.1 0.1]", "depth_to": "[0.1 0.1]", "network": "IMA-CAN1"}, "geometry": {"type": "Point", "coordinates": [8.62649, 44.68286]}}, {"type": "Feature", "properties": {"station_name": "station6", "depth_from": "[0.1 0.1]", "depth_to": "[0.1 0.1]", "network": "IMA-CAN1"}, "geometry": {"type": "Point", "coordinates": [8.62649, 44.68287]}}, {"type": "Feature", "properties": {"station_name": "station7", "depth_from": "[0.1 0.1]", "depth_to": "[0.1 0.1]", "network": "IMA-CAN1"}, "geometry": {"type": "Point", "coordinates": [8.62684, 44.68265]}}, {"type": "Feature", "properties": {"station_name": "station8", "depth_from": "[0.1 0.1]", "depth_to": "[0.1 0.1]", "network": "IMA-CAN1"}, "geometry": {"type": "Point", "coordinates": [8.62685, 44.68265]}}, {"type": "Feature", "properties": {"station_name": "station9", "depth_from": "[0.1 0.1]", "depth_to": "[0.1 0.1]", "network": "IMA-CAN1"}, "geometry": {"type": "Point", "coordinates": [8.62635, 44.68275]}}]}